conventionalrp-1.2.1.dist-info/METADATA
conventionalrp-1.2.1.dist-info/WHEEL
conventionalrp-1.2.1.dist-info/licenses/LICENSE
conventionalrp/__init__.py
conventionalrp/__main__.py
conventionalrp/_core.abi3.so
conventionalrp/_core.pyi
conventionalrp/core/__init__.py
conventionalrp/core/auto_parser.py
conventionalrp/core/parser.py
conventionalrp/core/processor.py
conventionalrp/core/rules.py
conventionalrp/core/thulac_parser.py
conventionalrp/extractors/__init__.py
conventionalrp/extractors/base.py
conventionalrp/extractors/rule_extractor.py
conventionalrp/plugins/__init__.py
conventionalrp/plugins/base.py
conventionalrp/plugins/plugin_manager.py
conventionalrp/renderers/__init__.py
conventionalrp/renderers/base.py
conventionalrp/renderers/html_renderer.py
conventionalrp/renderers/json_renderer.py
conventionalrp/renderers/markdown_renderer.py
conventionalrp/utils/__init__.py
conventionalrp/utils/exceptions.py
conventionalrp/utils/logging_config.py
conventionalrp/utils/visualize_relations.py
conventionalrp-1.2.1.dist-info/RECORD
