Metadata-Version: 2.4
Name: conventionalrp
Version: 1.2.1
Classifier: Development Status :: 5 - Production/Stable
Classifier: Framework :: Robot Framework
Classifier: Framework :: Robot Framework :: Library
Classifier: Operating System :: OS Independent
Classifier: Programming Language :: Python :: 3
Classifier: Programming Language :: Rust
Classifier: Programming Language :: Python :: Implementation :: CPython
Classifier: Programming Language :: Python :: Implementation :: PyPy
Requires-Dist: graphviz>=0.21
Requires-Dist: hanlp>=2.1.3
Requires-Dist: hanlp-restful>=0.0.24
Requires-Dist: snownlp>=0.12.3
License-File: LICENSE
Summary: HydroRoll Conventional Role Play SDK
Keywords: hydroroll
Home-Page: https://crp.hydroroll.team/
Author-email: HsiangNianian <leader@hydroroll.team>
License: AGPLv3.0
Requires-Python: >=3.9
Project-URL: homepage, https://hydroroll.team/
Project-URL: repository, https://github.com/HydroRoll-Team/conventional_role_play
Project-URL: documentation, https://crp.hydroroll.team/
